omnidim/__init__.py
omnidim/client.py
omnidim/resources/__init__.py
omni_assistant_sdk-0.1.0.dist-info/LICENSE
omni_assistant_sdk-0.1.0.dist-info/METADATA
omni_assistant_sdk-0.1.0.dist-info/WHEEL
omni_assistant_sdk-0.1.0.dist-info/top_level.txt
omni_assistant_sdk-0.1.0.dist-info/RECORD
