Metadata-Version: 2.1
Name: omni-assistant-sdk
Version: 0.1.0
Summary: Minimal SDK for Omni Assistant services
Home-page: https://github.com/kevin-omnidim/omnidim-sdk
Author: https://www.omnidim.io/
Author-email: shounak@omnidim.io
Classifier: Programming Language :: Python :: 3
Classifier: License :: OSI Approved :: MIT License
Classifier: Operating System :: OS Independent
Requires-Python: >=3.6
License-File: LICENSE
Requires-Dist: requests
